loader.cp313-win_amd64.pyd
fafig_studio-1.0.1.dist-info/METADATA
fafig_studio-1.0.1.dist-info/WHEEL
fafig_studio-1.0.1.dist-info/top_level.txt
fafig_studio-1.0.1.dist-info/RECORD
